gameoflife/__init__.py
gameoflife/gameOfLife.py
gameoflife/runGameOfLife.py
gameoflife/testGOL.py
uu_tora_gameoflife-0.0.1.dist-info/METADATA
uu_tora_gameoflife-0.0.1.dist-info/WHEEL
uu_tora_gameoflife-0.0.1.dist-info/top_level.txt
uu_tora_gameoflife-0.0.1.dist-info/RECORD
