Metadata-Version: 2.1
Name: uu-tora-gameoflife
Version: 0.0.1
Summary: Implementation of Conways Game of Life
Author: Tora Hävermark
Author-email: <tora.havermark@icm.uu.se>
License: UNKNOWN
Platform: UNKNOWN
Requires-Dist: numpy
Requires-Dist: matplotlib
